cythonuniquedim/README.MD
cythonuniquedim/__init__.py
cythonuniquedim/gmp.h
cythonuniquedim/mpc.h
cythonuniquedim/mpfr.h
cythonuniquedim/requirements.txt
cythonuniquedim/thirdparty.json
cythonuniquedim-0.10.dist-info/LICENSE.rst
cythonuniquedim-0.10.dist-info/METADATA
cythonuniquedim-0.10.dist-info/WHEEL
cythonuniquedim-0.10.dist-info/top_level.txt
cythonuniquedim-0.10.dist-info/RECORD
