Metadata-Version: 2.1
Name: cythonuniquedim
Version: 0.10
Summary: Finds unique dimensions in multi-dimensional arrays, compresses and decompresses arrays ...
Home-page: https://github.com/hansalemaos/cythonuniquedim
Author: Johannes Fischer
Author-email: aulasparticularesdealemaosp@gmail.com
License: GPL3
Keywords: cython,arrays
Classifier: Development Status :: 4 - Beta
Classifier: Programming Language :: Python :: 3 :: Only
Classifier: Programming Language :: Python :: 3.10
Classifier: Topic :: Software Development :: Libraries :: Python Modules
Classifier: Topic :: Utilities
License-File: LICENSE.rst
Requires-Dist: Cython
Requires-Dist: cythonanyarray
Requires-Dist: gmpy2
Requires-Dist: numpy
